net_report/__init__.py
net_report/args.py
net_report/colors.py
net_report/config.py
net_report/host.py
net_report/results.py
netreport-0.0.4.dist-info/METADATA
netreport-0.0.4.dist-info/WHEEL
netreport-0.0.4.dist-info/entry_points.txt
netreport-0.0.4.dist-info/top_level.txt
netreport-0.0.4.dist-info/RECORD
