Metadata-Version: 2.2
Name: NetReport
Version: 0.0.4
Summary: Quick view into server status
Home-page: https://github.com/samfelt/NetReport
Author: samfelt
Classifier: Programming Language :: Python :: 3
Classifier: Programming Language :: Python :: 3.11
Classifier: License :: OSI Approved :: GNU General Public License v3 or later (GPLv3+)
Requires-Dist: icmplib>=3.0.4
Requires-Dist: tabulate>=0.9.0
